hydrosolver/composition.py
hydrosolver/optimization.py
hydrosolver/solution.py
hydrosolver/utils.py
hydrosolver/version.py
hydrosolver/database/altea.yaml
hydrosolver/database/buyferti.yaml
hydrosolver/database/chelates.yaml
hydrosolver/database/compo.yaml
hydrosolver/database/howard_resh.yaml
hydrosolver/database/masterblend.yaml
hydrosolver/database/pure.yaml
hydrosolver/database/test.yaml
hydrosolver/database/water.yaml
hydrosolver-0.1.dist-info/LICENSE.md
hydrosolver-0.1.dist-info/METADATA
hydrosolver-0.1.dist-info/WHEEL
hydrosolver-0.1.dist-info/top_level.txt
hydrosolver-0.1.dist-info/RECORD
