Metadata-Version: 2.1
Name: hydrosolver
Version: 0.1
Summary: Optimization driven hydroponic nutrient calculator and a domain-specific language.
Home-page: https://github.com/dstrelnikov/hydrosolver
Author: Dmytro Strelnikov
Author-email: d.strelnikov@inventati.org,
License: GPL v3
Project-URL: Documentation, https://hydrosolver.readthedocs.io/
Project-URL: Source, https://github.com/dstrelnikov/hydrosolver
Keywords: hydroponics,growing,domain-specific-language,optimizer
Platform: UNKNOWN
Classifier: Environment :: Console
Classifier: Intended Audience :: Science/Research
Classifier: Natural Language :: English
Classifier: Operating System :: POSIX :: Linux
Classifier: Programming Language :: Python :: 3.6
Classifier: Programming Language :: Python :: 3.7
Classifier: Programming Language :: Python :: 3.8
Classifier: Programming Language :: Python :: 3.9
Requires-Python: >=3.6
License-File: LICENSE.md
Requires-Dist: numpy (>=1.13.1)
Requires-Dist: tabulate (>=0.8.9)
Requires-Dist: PyYAML (>=5.4.1)
